MANIFEST.in
Makefile
README
setup.py
tiddlywebplugins/__init__.py
tiddlywebplugins/plugins.py
tiddlywebplugins.plugins.egg-info/PKG-INFO
tiddlywebplugins.plugins.egg-info/SOURCES.txt
tiddlywebplugins.plugins.egg-info/dependency_links.txt
tiddlywebplugins.plugins.egg-info/namespace_packages.txt
tiddlywebplugins.plugins.egg-info/not-zip-safe
tiddlywebplugins.plugins.egg-info/requires.txt
tiddlywebplugins.plugins.egg-info/top_level.txt