Metadata-Version: 1.0
Name: tiddlywebplugins.plugins
Version: 0.2
Summary: A TiddlyWeb plugin for flexibly managing system_plugins.
Home-page: http://pypi.python.org/pypi/tiddlywebplugins.plugins
Author: Chris Dent
Author-email: cdent@peermore.com
License: UNKNOWN
Platform: Posix; MacOS X; Windows
